pypi_parker/__init__.py
pypi_parker/build.py
pypi_parker/config.py
pypi_parker/util.py
pypi_parker/utils.py
pypi_parker-0.1.2.dist-info/DESCRIPTION.rst
pypi_parker-0.1.2.dist-info/LICENSE.txt
pypi_parker-0.1.2.dist-info/METADATA
pypi_parker-0.1.2.dist-info/RECORD
pypi_parker-0.1.2.dist-info/WHEEL
pypi_parker-0.1.2.dist-info/entry_points.txt
pypi_parker-0.1.2.dist-info/metadata.json
pypi_parker-0.1.2.dist-info/top_level.txt
