Metadata-Version: 2.0
Name: pypi-parker
Version: 0.1.2
Summary: UNKNOWN
Home-page: https://github.com/mattsb42/pypi-parker
Author: Matt Bullock
Author-email: matt.s.b.42@gmail.com
License: Apache License 2.0
Keywords: pypi warehouse distutils typosquating
Platform: UNKNOWN
Classifier: Development Status :: 4 - Beta
Classifier: Intended Audience :: Developers
Classifier: Natural Language :: English
Classifier: License :: OSI Approved :: Apache Software License
Classifier: Programming Language :: Python
Classifier: Programming Language :: Python :: 3
Classifier: Programming Language :: Python :: 3.6
Classifier: Programming Language :: Python :: Implementation :: CPython
Classifier: Topic :: System :: Software Distribution
Classifier: Topic :: Utilities
Requires-Dist: readme-renderer (>=17.2)
